.gitignore
MANIFEST.in
README.rst
bootstrap.py
buildout.cfg
setup.py
Products/__init__.py
Products.CalendarX.egg-info/PKG-INFO
Products.CalendarX.egg-info/SOURCES.txt
Products.CalendarX.egg-info/dependency_links.txt
Products.CalendarX.egg-info/entry_points.txt
Products.CalendarX.egg-info/namespace_packages.txt
Products.CalendarX.egg-info/not-zip-safe
Products.CalendarX.egg-info/requires.txt
Products.CalendarX.egg-info/top_level.txt
Products/CalendarX/CalendarXFolder.py
Products/CalendarX/README.txt
Products/CalendarX/__init__.py
Products/CalendarX/config.py
Products/CalendarX/refresh.txt
Products/CalendarX/docs/CREDITS.txt
Products/CalendarX/docs/CUSTOM.txt
Products/CalendarX/docs/INSTALL.txt
Products/CalendarX/docs/LICENSE.GPL
Products/CalendarX/docs/LICENSE.txt
Products/CalendarX/docs/MIGRATE.txt
Products/CalendarX/docs/OVERVIEW.txt
Products/CalendarX/docs/TODO.txt
Products/CalendarX/i18n/calendarx-ca.po
Products/CalendarX/i18n/calendarx-cs.po
Products/CalendarX/i18n/calendarx-da.po
Products/CalendarX/i18n/calendarx-de.po
Products/CalendarX/i18n/calendarx-en.po
Products/CalendarX/i18n/calendarx-es.po
Products/CalendarX/i18n/calendarx-fi.po
Products/CalendarX/i18n/calendarx-fr.po
Products/CalendarX/i18n/calendarx-it.po
Products/CalendarX/i18n/calendarx-ja.po
Products/CalendarX/i18n/calendarx-nl.po
Products/CalendarX/i18n/calendarx-pt-br.po
Products/CalendarX/i18n/calendarx-sv.po
Products/CalendarX/i18n/calendarx.pot
Products/CalendarX/i18n/plone-calendarx-fr.po
Products/CalendarX/i18n/plone-calendarx.pot
Products/CalendarX/model/CalendarX.uml
Products/CalendarX/profiles/default/metadata.xml
Products/CalendarX/profiles/default/skins.xml
Products/CalendarX/profiles/default/types.xml
Products/CalendarX/profiles/default/types/CalendarXFolder.xml
Products/CalendarX/skins/CalendarX/CX_props_macros.pt
Products/CalendarX/skins/CalendarX/CalendarX16.gif
Products/CalendarX/skins/CalendarX/atevent_icon.gif
Products/CalendarX/skins/CalendarX/calLinkOpaque.gif
Products/CalendarX/skins/CalendarX/calendar.065.js
Products/CalendarX/skins/CalendarX/calendar.css.dtml
Products/CalendarX/skins/CalendarX/calendar.js.dtml
Products/CalendarX/skins/CalendarX/calendarPrint.css.dtml
Products/CalendarX/skins/CalendarX/day.css.dtml
Products/CalendarX/skins/CalendarX/day.pt
Products/CalendarX/skins/CalendarX/dhtml.js
