Metadata-Version: 1.1
Name: Products.CalendarX
Version: 1.0.3
Summary: CalendarX is a customizable, open source metacalendar application written for the Plone content management system on top of Zope and Python.
Home-page: https://github.com/collective/Products.CalendarX
Author: Alex Clark
Author-email: aclark@aclark.net
License: GPL
Keywords: plone calendar
Platform: UNKNOWN
Classifier: Development Status :: 5 - Production/Stable
Classifier: Framework :: Plone
Classifier: Framework :: Zope2
Classifier: Programming Language :: Python
Classifier: Operating System :: OS Independent
Classifier: Topic :: Software Development :: Libraries :: Python Modules
Classifier: Topic :: Office/Business :: Scheduling
Classifier: Natural Language :: Catalan
Classifier: Natural Language :: Czech
Classifier: Natural Language :: Danish
Classifier: Natural Language :: English
Classifier: Natural Language :: German
Classifier: Natural Language :: French
Classifier: Natural Language :: Italian
Classifier: Natural Language :: Japanese
Classifier: Natural Language :: Dutch
Classifier: Natural Language :: Portuguese (Brazilian)
Classifier: Natural Language :: Swedish
